kaiko_research/__init__.py
kaiko_research/api_client.py
kaiko_research/endpoint_schemas.py
kaiko_research/kaiko.py
kaiko_research/request_handler.py
kaiko_research/utils.py
kaiko_research-0.0.17.dist-info/LICENSE.txt
kaiko_research-0.0.17.dist-info/METADATA
kaiko_research-0.0.17.dist-info/WHEEL
kaiko_research-0.0.17.dist-info/top_level.txt
kaiko_research-0.0.17.dist-info/RECORD
