Metadata-Version: 2.1
Name: kaiko-research
Version: 0.0.17
Summary: An API wrapper for Kaiko data containing the information about data exports, parameters for each export and methods to fetch raw data or pre-processed data based on experience of Kaiko research intelligence
Home-page: https://github.com/kaikodata/research-scripts
Author: Evgeny Ryabchenkov
Author-email: evgeny.ryabchenkov@kaiko.com
Classifier: Programming Language :: Python :: 3
Classifier: License :: OSI Approved :: MIT License
Classifier: Operating System :: OS Independent
Requires-Python: >=3.6
License-File: LICENSE.txt
Requires-Dist: cerberus
Requires-Dist: dask
Requires-Dist: datetime
Requires-Dist: pandas
Requires-Dist: requests
Requires-Dist: tqdm
